sonic.cpython-37m-x86_64-linux-gnu.so
sonicpy-0.1.2.dist-info/RECORD
sonicpy-0.1.2.dist-info/METADATA
sonicpy-0.1.2.dist-info/top_level.txt
sonicpy-0.1.2.dist-info/LICENSE
sonicpy-0.1.2.dist-info/WHEEL
